{
  "allVideos": [
    {
      "id": "121e",
      "caption": "Ballatha Jathi",
      "imgUrl": "https://i.ytimg.com/vi/rhrD7as3KJg/maxresdefault.jpg",
      "link": "https://www.youtube.com/embed/rhrD7as3KJg?si=1txNLbxWI4YS4fOz"
    },
    {
      "id": "05f5",
      "caption": "ARM Trailer",
      "imgUrl": "https://i.ytimg.com/vi/rFgS10V8908/maxresdefault.jpg",
      "link": "https://www.youtube.com/embed/rFgS10V8908?si=jHACMuPhhg1MLccv"
    },
    {
      "id": "d1d5",
      "caption": "Deadpool 3",
      "imgUrl": "https://i.ytimg.com/vi/5dOd81S7CU8/maxresdefault.jpg",
      "link": "https://www.youtube.com/embed/cen0rBKLuYE?si=GZ_EaR0oGNbM3Oxv"
    },
    {
      "id": "5a33",
      "caption": "Pani",
      "imgUrl": "https://i.ytimg.com/vi/r8IP4qzPXVU/maxresdefault.jpg",
      "link": "https://www.youtube.com/embed/r8IP4qzPXVU?si=O1ksBCnYSuKq0OCq"
    },
    {
      "id": "830e",
      "caption": "Ordinary Person",
      "imgUrl": "https://i.ytimg.com/vi/q6e_b0NERCA/maxresdefault.jpg",
      "link": "https://www.youtube.com/embed/q6e_b0NERCA?si=-AYC8U_hnNDBBO9Z"
    },
    {
      "id": "8ac4",
      "caption": "Ayyayyo",
      "imgUrl": "https://i.ytimg.com/vi/5LGfP-BSJ8M/hq720.jpg?sqp=-oaymwEhCK4FEIIDSFryq4qpAxMIARUAAAAAGAElAADIQj0AgKJD&rs=AOn4CLBZUJeg7KUAbEFvlV0n3JjTu6x_Vw",
      "link": "https://www.youtube.com/embed/1w2-agE-Dtk?si=HrTZnB1e37UBCdAk"
    },
    {
      "id": "5e13",
      "caption": "Naa Ready",
      "imgUrl": "https://i.ytimg.com/vi/3wDiqlTNlfQ/maxresdefault.jpg",
      "link": "https://www.youtube.com/embed/3wDiqlTNlfQ?si=9WqnKoqBGMT4p4qo"
    },
    {
      "id": "af78",
      "caption": "After Hours",
      "imgUrl": "https://i.ytimg.com/vi/ygTZZpVkmKg/maxresdefault.jpg?sqp=-oaymwEmCIAKENAF8quKqQMa8AEB-AH-CYAC0AWKAgwIABABGGUgYChBMA8=&rs=AOn4CLCGyq5LXGqbqjoSvDAgtrN35VrSVg",
      "link": "https://www.youtube.com/embed/ygTZZpVkmKg?si=EwlkvRPIwusyMS_U"
    },
    {
      "id": "2733",
      "caption": "Leo",
      "imgUrl": "https://i.ytimg.com/vi/Po3jStA673E/maxresdefault.jpg",
      "link": "https://www.youtube.com/embed/Po3jStA673E?si=5HUf2FdTVXv4ZQAl"
    }
  ],
  "category": [
    {
      "id": "6449",
      "addCateogry": "Trailers",
      "allVideos": [
        {
          "id": "d1d5",
          "caption": "Deadpool 3",
          "imgUrl": "https://i.ytimg.com/vi/5dOd81S7CU8/maxresdefault.jpg",
          "link": "https://www.youtube.com/embed/cen0rBKLuYE?si=GZ_EaR0oGNbM3Oxv"
        },
        {
          "id": "05f5",
          "caption": "ARM Trailer",
          "imgUrl": "https://i.ytimg.com/vi/rFgS10V8908/maxresdefault.jpg",
          "link": "https://www.youtube.com/embed/rFgS10V8908?si=jHACMuPhhg1MLccv"
        },
        {
          "id": "5a33",
          "caption": "Pani",
          "imgUrl": "https://i.ytimg.com/vi/r8IP4qzPXVU/maxresdefault.jpg",
          "link": "https://www.youtube.com/embed/r8IP4qzPXVU?si=O1ksBCnYSuKq0OCq"
        },
        {
          "id": "2733",
          "caption": "Leo",
          "imgUrl": "https://i.ytimg.com/vi/Po3jStA673E/maxresdefault.jpg",
          "link": "https://www.youtube.com/embed/Po3jStA673E?si=5HUf2FdTVXv4ZQAl"
        }
      ]
    },
    {
      "id": "2011",
      "addCateogry": "Music",
      "allVideos": [
        {
          "id": "830e",
          "caption": "Ordinary Person",
          "imgUrl": "https://i.ytimg.com/vi/q6e_b0NERCA/maxresdefault.jpg",
          "link": "https://www.youtube.com/embed/q6e_b0NERCA?si=-AYC8U_hnNDBBO9Z"
        },
        {
          "id": "8ac4",
          "caption": "Ayyayyo",
          "imgUrl": "https://i.ytimg.com/vi/5LGfP-BSJ8M/hq720.jpg?sqp=-oaymwEhCK4FEIIDSFryq4qpAxMIARUAAAAAGAElAADIQj0AgKJD&rs=AOn4CLBZUJeg7KUAbEFvlV0n3JjTu6x_Vw",
          "link": "https://www.youtube.com/embed/1w2-agE-Dtk?si=HrTZnB1e37UBCdAk"
        },
        {
          "id": "121e",
          "caption": "Ballatha Jathi",
          "imgUrl": "https://i.ytimg.com/vi/rhrD7as3KJg/maxresdefault.jpg",
          "link": "https://www.youtube.com/embed/rhrD7as3KJg?si=1txNLbxWI4YS4fOz"
        },
        {
          "id": "5e13",
          "caption": "Naa Ready",
          "imgUrl": "https://i.ytimg.com/vi/3wDiqlTNlfQ/maxresdefault.jpg",
          "link": "https://www.youtube.com/embed/3wDiqlTNlfQ?si=9WqnKoqBGMT4p4qo"
        },
        {
          "id": "af78",
          "caption": "After Hours",
          "imgUrl": "https://i.ytimg.com/vi/ygTZZpVkmKg/maxresdefault.jpg?sqp=-oaymwEmCIAKENAF8quKqQMa8AEB-AH-CYAC0AWKAgwIABABGGUgYChBMA8=&rs=AOn4CLCGyq5LXGqbqjoSvDAgtrN35VrSVg",
          "link": "https://www.youtube.com/embed/ygTZZpVkmKg?si=EwlkvRPIwusyMS_U"
        }
      ]
    }
  ],
  "watchHistory": [
    {
      "id": "da0b",
      "caption": "Chromakopia",
      "link": "https://www.youtube.com/embed/lbbTFxMIEWQ?si=YrMUgkrOxxm0-zb1",
      "timestamp": "11/07/24, 09:10:41 AM"
    },
    {
      "id": "e6f6",
      "caption": "One of Wun",
      "link": "https://www.youtube.com/embed/HqiZRQHhqQs?si=mIHlSU1CPEnng9my",
      "timestamp": "11/07/24, 09:11:01 AM"
    },
    {
      "id": "c221",
      "caption": "DNA",
      "link": "https://www.youtube.com/embed/uX6uBHPGfSs?si=BE7xo8PNo5NKZWXU",
      "timestamp": "11/07/24, 10:34:28 AM"
    },
    {
      "id": "e191",
      "caption": "Ordinary Person",
      "link": "https://www.youtube.com/embed/q6e_b0NERCA?si=-AYC8U_hnNDBBO9Z",
      "timestamp": "11/07/24, 07:11:22 PM"
    },
    {
      "id": "7792",
      "caption": "Pani",
      "link": "https://www.youtube.com/embed/r8IP4qzPXVU?si=O1ksBCnYSuKq0OCq",
      "timestamp": "11/07/24, 07:11:45 PM"
    },
    {
      "id": "5869",
      "caption": "Naa Ready",
      "link": "https://www.youtube.com/embed/3wDiqlTNlfQ?si=9WqnKoqBGMT4p4qo",
      "timestamp": "11/07/24, 07:11:57 PM"
    },
    {
      "id": "35fa",
      "caption": "Leo",
      "link": "https://www.youtube.com/embed/Po3jStA673E?si=5HUf2FdTVXv4ZQAl",
      "timestamp": "11/07/24, 07:12:01 PM"
    },
    {
      "id": "3535",
      "caption": "After Hours",
      "link": "https://www.youtube.com/embed/ygTZZpVkmKg?si=EwlkvRPIwusyMS_U",
      "timestamp": "11/07/24, 07:12:06 PM"
    }
  ]
}